setup.py
gaussian_binomial_distributions/Binomialdistribution.py
gaussian_binomial_distributions/Gaussiandistribution.py
gaussian_binomial_distributions/Generaldistribution.py
gaussian_binomial_distributions/__init__.py
gaussian_binomial_distributions.egg-info/PKG-INFO
gaussian_binomial_distributions.egg-info/SOURCES.txt
gaussian_binomial_distributions.egg-info/dependency_links.txt
gaussian_binomial_distributions.egg-info/not-zip-safe
gaussian_binomial_distributions.egg-info/top_level.txt